tableformatter.py
tableformatter-0.1.6.dist-info/LICENSE
tableformatter-0.1.6.dist-info/METADATA
tableformatter-0.1.6.dist-info/WHEEL
tableformatter-0.1.6.dist-info/top_level.txt
tableformatter-0.1.6.dist-info/RECORD
