Metadata-Version: 2.1
Name: tableformatter
Version: 0.1.6
Summary: python-tableformatter - Tabular data formatter allowing printing from both arbitrary tuples of strings or object inspection
Home-page: https://github.com/python-tableformatter/tableformatter
Author: Eric Lin
Author-email: anselor@gmail.com
License: MIT
Keywords: table tabular formatter
Platform: any
Classifier: Development Status :: 5 - Production/Stable
Classifier: Environment :: Console
Classifier: Operating System :: OS Independent
Classifier: Intended Audience :: Developers
Classifier: Intended Audience :: System Administrators
Classifier: License :: OSI Approved :: MIT License
Classifier: Programming Language :: Python
Classifier: Programming Language :: Python :: 3
Classifier: Programming Language :: Python :: 3.4
Classifier: Programming Language :: Python :: 3.5
Classifier: Programming Language :: Python :: 3.6
Classifier: Programming Language :: Python :: 3.7
Classifier: Programming Language :: Python :: 3.8
Classifier: Programming Language :: Python :: Implementation :: CPython
Classifier: Topic :: Software Development :: Libraries :: Python Modules
Requires-Python: >=3.4
Requires-Dist: wcwidth
Requires-Dist: typing ; python_version<'3.5'
Provides-Extra: dev
Requires-Dist: invoke ; extra == 'dev'
Requires-Dist: pytest ; extra == 'dev'
Requires-Dist: pytest-cov ; extra == 'dev'
Requires-Dist: setuptools (>=39.1) ; extra == 'dev'
Requires-Dist: tox ; extra == 'dev'
Requires-Dist: twine (>=1.11) ; extra == 'dev'
Requires-Dist: wheel (>=0.31) ; extra == 'dev'
